gf_account_de_skr04-7.8.0.dist-info/licenses/LICENSE
trytond/modules/account_de_skr04_I/__init__.py
trytond/modules/account_de_skr04_I/account_template.xml
trytond/modules/account_de_skr04_I/account_type_template.xml
trytond/modules/account_de_skr04_I/tax_code_line_template.xml
trytond/modules/account_de_skr04_I/tax_code_template.xml
trytond/modules/account_de_skr04_I/tax_group.xml
trytond/modules/account_de_skr04_I/tax_rule_template.xml
trytond/modules/account_de_skr04_I/tax_template.xml
trytond/modules/account_de_skr04_I/tryton.cfg
trytond/modules/account_de_skr04_I/tests/__init__.py
trytond/modules/account_de_skr04_I/tests/test_module.py
gf_account_de_skr04-7.8.0.dist-info/METADATA
gf_account_de_skr04-7.8.0.dist-info/WHEEL
gf_account_de_skr04-7.8.0.dist-info/entry_points.txt
gf_account_de_skr04-7.8.0.dist-info/top_level.txt
gf_account_de_skr04-7.8.0.dist-info/RECORD
